langid_indian/__init__.py
langid_indian/model_loader.py
langid_indian/predictor.py
langid_indian-0.1.4.dist-info/licenses/LICENSE
langid_indian-0.1.4.dist-info/METADATA
langid_indian-0.1.4.dist-info/WHEEL
langid_indian-0.1.4.dist-info/top_level.txt
langid_indian-0.1.4.dist-info/RECORD
